setup.py
funieest.egg-info/PKG-INFO
funieest.egg-info/SOURCES.txt
funieest.egg-info/dependency_links.txt
funieest.egg-info/not-zip-safe
funieest.egg-info/top_level.txt
funniest/__init__.py