Metadata-Version: 1.0
Name: funieest
Version: 0.2
Summary: The funniest joke in the world
Home-page: https://github.com/hamadi15/test
Author: halim hamadi
Author-email: halim.hamadi@mail.ugm.ac.id
License: MIT
Platform: UNKNOWN
